README.rst
setup.py
Tigger.egg-info/PKG-INFO
Tigger.egg-info/SOURCES.txt
Tigger.egg-info/dependency_links.txt
Tigger.egg-info/entry_points.txt
Tigger.egg-info/top_level.txt
tigger/__init__.py
tigger/app.py
tigger/core.py
tigger/error.py