Metadata-Version: 1.1
Name: Tigger
Version: 0.1.1
Summary: Command-line tagging tool.
Home-page: https://github.com/bit-shift/tigger
Author: Bit Shift
Author-email: bitshift@bigmacintosh.net
License: MIT
Platform: UNKNOWN
Classifier: Programming Language :: Python
Classifier: Programming Language :: Python :: 3
Classifier: License :: OSI Approved :: MIT License
Classifier: Operating System :: OS Independent
Classifier: Development Status :: 4 - Beta
Classifier: Environment :: Console
Classifier: Topic :: Utilities
